PyQC/__init__.py
PyQC/aes.py
PyQC/ccakem.py
PyQC/cpake.py
PyQC/crypto.py
PyQC/data.py
PyQC/date_utils.py
PyQC/indcpa.py
PyQC/kyber_token.py
PyQC/ntt.py
PyQC/params.py
PyQC/poly.py
PyQC/prf.py
PyQC/requests_utils.py
PyQC/session_key_iter.py
PyQC/util.py
PyQC-0.0.3.dist-info/METADATA
PyQC-0.0.3.dist-info/WHEEL
PyQC-0.0.3.dist-info/top_level.txt
PyQC-0.0.3.dist-info/RECORD
