Metadata-Version: 2.1
Name: PyQC
Version: 0.0.3
Summary: UNKNOWN
Home-page: UNKNOWN
Author: PyRiscV
Author-email: pyriscv@gmail.com
License: MIT
Platform: UNKNOWN
Classifier: License :: OSI Approved :: MIT License
Classifier: Programming Language :: Python
Classifier: Programming Language :: Python :: 3
Requires-Dist: httpx
Requires-Dist: pycryptodome
